{
  "昨晚做了个梦，梦见自己探索外星球，把梦境描述给 AI 一篇科幻文出来了（AI 强大）_0": {
    "title": "昨晚做了个梦，梦见自己探索外星球，把梦境描述给 AI 一篇科幻文出来了（AI 强大）",
    "source_name": "v2ex",
    "ranks": [
      1
    ],
    "time_info": "",
    "count": 0,
    "url": "https://www.v2ex.com/t/1165176",
    "mobile_url": "https://www.v2ex.com/t/1165176",
    "hot_value": 0
  },
  "T-Mobile $3 保号卡已无免费通话时长和短信_1": {
    "title": "T-Mobile $3 保号卡已无免费通话时长和短信",
    "source_name": "v2ex",
    "ranks": [
      2
    ],
    "time_info": "",
    "count": 0,
    "url": "https://www.v2ex.com/t/1165174",
    "mobile_url": "https://www.v2ex.com/t/1165174",
    "hot_value": 0
  },
  "SEE Conf 2025 来啦，一起探索 AI 时代的用户体验与工程实践！_2": {
    "title": "SEE Conf 2025 来啦，一起探索 AI 时代的用户体验与工程实践！",
    "source_name": "v2ex",
    "ranks": [
      3
    ],
    "time_info": "",
    "count": 0,
    "url": "https://www.v2ex.com/t/1165171",
    "mobile_url": "https://www.v2ex.com/t/1165171",
    "hot_value": 0
  },
  "WhatsApp 协议怎么这么复杂_3": {
    "title": "WhatsApp 协议怎么这么复杂",
    "source_name": "v2ex",
    "ranks": [
      4
    ],
    "time_info": "",
    "count": 0,
    "url": "https://www.v2ex.com/t/1165161",
    "mobile_url": "https://www.v2ex.com/t/1165161",
    "hot_value": 0
  },
  "最近依赖上 copilot 了，有没有用过 Pro+的 V 友知道有多少次 premium requests？_4": {
    "title": "最近依赖上 copilot 了，有没有用过 Pro+的 V 友知道有多少次 premium requests？",
    "source_name": "v2ex",
    "ranks": [
      5
    ],
    "time_info": "",
    "count": 0,
    "url": "https://www.v2ex.com/t/1165143",
    "mobile_url": "https://www.v2ex.com/t/1165143",
    "hot_value": 0
  },
  "跌跌不休，来心理按摩按摩_5": {
    "title": "跌跌不休，来心理按摩按摩",
    "source_name": "v2ex",
    "ranks": [
      6
    ],
    "time_info": "",
    "count": 0,
    "url": "https://www.v2ex.com/t/1165136",
    "mobile_url": "https://www.v2ex.com/t/1165136",
    "hot_value": 0
  },
  "妙语 - 桌面端语音输入工具（Wispr Flow 开源替代）_6": {
    "title": "妙语 - 桌面端语音输入工具（Wispr Flow 开源替代）",
    "source_name": "v2ex",
    "ranks": [
      7
    ],
    "time_info": "",
    "count": 0,
    "url": "https://www.v2ex.com/t/1165137",
    "mobile_url": "https://www.v2ex.com/t/1165137",
    "hot_value": 0
  },
  "分享 2 个外卖返利的软件_7": {
    "title": "分享 2 个外卖返利的软件",
    "source_name": "v2ex",
    "ranks": [
      8
    ],
    "time_info": "",
    "count": 0,
    "url": "https://www.v2ex.com/t/1165116",
    "mobile_url": "https://www.v2ex.com/t/1165116",
    "hot_value": 0
  },
  "sora2 api 站 xiaoai.io_8": {
    "title": "sora2 api 站 xiaoai.io",
    "source_name": "v2ex",
    "ranks": [
      9
    ],
    "time_info": "",
    "count": 0,
    "url": "https://www.v2ex.com/t/1165115",
    "mobile_url": "https://www.v2ex.com/t/1165115",
    "hot_value": 0
  },
  "做了一个晨间练声的 iOS App 叫「吱吱练声」，适合所有喜欢唱歌的朋友，无套路送码_9": {
    "title": "做了一个晨间练声的 iOS App 叫「吱吱练声」，适合所有喜欢唱歌的朋友，无套路送码",
    "source_name": "v2ex",
    "ranks": [
      10
    ],
    "time_info": "",
    "count": 0,
    "url": "https://www.v2ex.com/t/1165114",
    "mobile_url": "https://www.v2ex.com/t/1165114",
    "hot_value": 0
  },
  "这两天突发奇想整了下车控的 APP_10": {
    "title": "这两天突发奇想整了下车控的 APP",
    "source_name": "v2ex",
    "ranks": [
      11
    ],
    "time_info": "",
    "count": 0,
    "url": "https://www.v2ex.com/t/1164803",
    "mobile_url": "https://www.v2ex.com/t/1164803",
    "hot_value": 0
  },
  "有对 comet 浏览器感兴趣的吗，注册领一个月 pro 会员。_11": {
    "title": "有对 comet 浏览器感兴趣的吗，注册领一个月 pro 会员。",
    "source_name": "v2ex",
    "ranks": [
      12
    ],
    "time_info": "",
    "count": 0,
    "url": "https://www.v2ex.com/t/1165090",
    "mobile_url": "https://www.v2ex.com/t/1165090",
    "hot_value": 0
  },
  "反向操作，给视频加上 Sora2 水印，假装是 Sora2_12": {
    "title": "反向操作，给视频加上 Sora2 水印，假装是 Sora2",
    "source_name": "v2ex",
    "ranks": [
      13
    ],
    "time_info": "",
    "count": 0,
    "url": "https://www.v2ex.com/t/1165088",
    "mobile_url": "https://www.v2ex.com/t/1165088",
    "hot_value": 0
  },
  "产品上线 google play, 找一些测试用户，送终身 VIP 会员_13": {
    "title": "产品上线 google play, 找一些测试用户，送终身 VIP 会员",
    "source_name": "v2ex",
    "ranks": [
      14
    ],
    "time_info": "",
    "count": 0,
    "url": "https://www.v2ex.com/t/1165082",
    "mobile_url": "https://www.v2ex.com/t/1165082",
    "hot_value": 0
  },
  "分享贴，国家 2006 年对 2020 年一些事情的预测_14": {
    "title": "分享贴，国家 2006 年对 2020 年一些事情的预测",
    "source_name": "v2ex",
    "ranks": [
      15
    ],
    "time_info": "",
    "count": 0,
    "url": "https://www.v2ex.com/t/1165067",
    "mobile_url": "https://www.v2ex.com/t/1165067",
    "hot_value": 0
  },
  "IG vs T1 说是 46 开， 4 点开始 6 点结束_15": {
    "title": "IG vs T1 说是 46 开， 4 点开始 6 点结束",
    "source_name": "v2ex",
    "ranks": [
      16
    ],
    "time_info": "",
    "count": 0,
    "url": "https://www.v2ex.com/t/1165063",
    "mobile_url": "https://www.v2ex.com/t/1165063",
    "hot_value": 0
  },
  "Hexo 静态博客使用 TouchID/FaceID/Yubikey/密码 加密解密文章_16": {
    "title": "Hexo 静态博客使用 TouchID/FaceID/Yubikey/密码 加密解密文章",
    "source_name": "v2ex",
    "ranks": [
      17
    ],
    "time_info": "",
    "count": 0,
    "url": "https://www.v2ex.com/t/1165058",
    "mobile_url": "https://www.v2ex.com/t/1165058",
    "hot_value": 0
  },
  "奔 4 的.NET 老兵，想深入 AI 大模型方向，但很迷茫_17": {
    "title": "奔 4 的.NET 老兵，想深入 AI 大模型方向，但很迷茫",
    "source_name": "v2ex",
    "ranks": [
      18
    ],
    "time_info": "",
    "count": 0,
    "url": "https://www.v2ex.com/t/1165052",
    "mobile_url": "https://www.v2ex.com/t/1165052",
    "hot_value": 0
  },
  "魔搭怎么不提供每个模型的详细使用次数查看呢_18": {
    "title": "魔搭怎么不提供每个模型的详细使用次数查看呢",
    "source_name": "v2ex",
    "ranks": [
      19
    ],
    "time_info": "",
    "count": 0,
    "url": "https://www.v2ex.com/t/1165033",
    "mobile_url": "https://www.v2ex.com/t/1165033",
    "hot_value": 0
  },
  "今天真是个好日子_19": {
    "title": "今天真是个好日子",
    "source_name": "v2ex",
    "ranks": [
      20
    ],
    "time_info": "",
    "count": 0,
    "url": "https://www.v2ex.com/t/1165029",
    "mobile_url": "https://www.v2ex.com/t/1165029",
    "hot_value": 0
  },
  "假期狂肝, 开源创意画板再晋级, 增加了许多有意思的功能, 欢迎体验_20": {
    "title": "假期狂肝, 开源创意画板再晋级, 增加了许多有意思的功能, 欢迎体验",
    "source_name": "v2ex",
    "ranks": [
      21
    ],
    "time_info": "",
    "count": 0,
    "url": "https://www.v2ex.com/t/1165021",
    "mobile_url": "https://www.v2ex.com/t/1165021",
    "hot_value": 0
  },
  "Si-Browser 2025 上架 Google Play 封闭式测试邀请_21": {
    "title": "Si-Browser 2025 上架 Google Play 封闭式测试邀请",
    "source_name": "v2ex",
    "ranks": [
      22
    ],
    "time_info": "",
    "count": 0,
    "url": "https://www.v2ex.com/t/1165007",
    "mobile_url": "https://www.v2ex.com/t/1165007",
    "hot_value": 0
  },
  "[播面-网页初版] 面试版小宇宙，主打用『耳朵』刷面试题_22": {
    "title": "[播面-网页初版] 面试版小宇宙，主打用『耳朵』刷面试题",
    "source_name": "v2ex",
    "ranks": [
      23
    ],
    "time_info": "",
    "count": 0,
    "url": "https://www.v2ex.com/t/1164875",
    "mobile_url": "https://www.v2ex.com/t/1164875",
    "hot_value": 0
  },
  "记得打卡 (PunchClock)：新手的第一个安卓 APP_23": {
    "title": "记得打卡 (PunchClock)：新手的第一个安卓 APP",
    "source_name": "v2ex",
    "ranks": [
      24
    ],
    "time_info": "",
    "count": 0,
    "url": "https://www.v2ex.com/t/1164965",
    "mobile_url": "https://www.v2ex.com/t/1164965",
    "hot_value": 0
  },
  "更新 V1.05, iPlay 最新版本，功能你懂的_24": {
    "title": "更新 V1.05, iPlay 最新版本，功能你懂的",
    "source_name": "v2ex",
    "ranks": [
      25
    ],
    "time_info": "",
    "count": 0,
    "url": "https://www.v2ex.com/t/1165003",
    "mobile_url": "https://www.v2ex.com/t/1165003",
    "hot_value": 0
  },
  "你比我猜：从派对游戏到社交神器的 40 年进化_25": {
    "title": "你比我猜：从派对游戏到社交神器的 40 年进化",
    "source_name": "v2ex",
    "ranks": [
      26
    ],
    "time_info": "",
    "count": 0,
    "url": "https://www.v2ex.com/t/1164960",
    "mobile_url": "https://www.v2ex.com/t/1164960",
    "hot_value": 0
  },
  "写八股文用 Gemini 还是 grok3？_26": {
    "title": "写八股文用 Gemini 还是 grok3？",
    "source_name": "v2ex",
    "ranks": [
      27
    ],
    "time_info": "",
    "count": 0,
    "url": "https://www.v2ex.com/t/1164991",
    "mobile_url": "https://www.v2ex.com/t/1164991",
    "hot_value": 0
  },
  "在 Hugo 静态博客中优雅地展示 LivePhotos 实况照片_27": {
    "title": "在 Hugo 静态博客中优雅地展示 LivePhotos 实况照片",
    "source_name": "v2ex",
    "ranks": [
      28
    ],
    "time_info": "",
    "count": 0,
    "url": "https://www.v2ex.com/t/1164982",
    "mobile_url": "https://www.v2ex.com/t/1164982",
    "hot_value": 0
  },
  "xsavenow.com 一个能下载 X/Twitter 文字图片视频的小工具（免登录/不收费）_28": {
    "title": "xsavenow.com 一个能下载 X/Twitter 文字图片视频的小工具（免登录/不收费）",
    "source_name": "v2ex",
    "ranks": [
      29
    ],
    "time_info": "",
    "count": 0,
    "url": "https://www.v2ex.com/t/1164976",
    "mobile_url": "https://www.v2ex.com/t/1164976",
    "hot_value": 0
  },
  "做了一个能下载 X/Twitter 视频的小工具（免登录 / 无水印）_29": {
    "title": "做了一个能下载 X/Twitter 视频的小工具（免登录 / 无水印）",
    "source_name": "v2ex",
    "ranks": [
      30
    ],
    "time_info": "",
    "count": 0,
    "url": "https://www.v2ex.com/t/1164966",
    "mobile_url": "https://www.v2ex.com/t/1164966",
    "hot_value": 0
  }
}